[{"awgn s/n": -30, "error rate": 0.8671328671328671, "message length": 143, "mode": "PSK125RC10", "simulation string": "\"AWGN_SNn30.0\",1,-30,0,0,0,0,0,0,0,0,0,0,0,0", "suffix": "AWGN_SNn30.0"}, {"awgn s/n": -25, "error rate": 0.8041958041958042, "message length": 143, "mode": "PSK125RC10", "simulation string": "\"AWGN_SNn25.0\",1,-25,0,0,0,0,0,0,0,0,0,0,0,0", "suffix": "AWGN_SNn25.0"}, {"awgn s/n": -20, "error rate": 0.8041958041958042, "message length": 143, "mode": "PSK125RC10", "simulation string": "\"AWGN_SNn20.0\",1,-20,0,0,0,0,0,0,0,0,0,0,0,0", "suffix": "AWGN_SNn20.0"}, {"awgn s/n": -15, "error rate": 0.8321678321678322, "message length": 143, "mode": "PSK125RC10", "simulation string": "\"AWGN_SNn15.0\",1,-15,0,0,0,0,0,0,0,0,0,0,0,0", "suffix": "AWGN_SNn15.0"}, {"awgn s/n": -10, "error rate": 0.8111888111888111, "message length": 143, "mode": "PSK125RC10", "simulation string": "\"AWGN_SNn10.0\",1,-10,0,0,0,0,0,0,0,0,0,0,0,0", "suffix": "AWGN_SNn10.0"}, {"awgn s/n": -5, "error rate": 0.5734265734265734, "message length": 143, "mode": "PSK125RC10", "simulation string": "\"AWGN_SNn05.0\",1,-5,0,0,0,0,0,0,0,0,0,0,0,0", "suffix": "AWGN_SNn05.0"}, {"awgn s/n": 0, "error rate": 0.0, "message length": 143, "mode": "PSK125RC10", "simulation string": "\"AWGN_SNp00.0\",1,0,0,0,0,0,0,0,0,0,0,0,0,0", "suffix": "AWGN_SNp00.0"}, {"awgn s/n": 5, "error rate": 0.0, "message length": 143, "mode": "PSK125RC10", "simulation string": "\"AWGN_SNp05.0\",1,5,0,0,0,0,0,0,0,0,0,0,0,0", "suffix": "AWGN_SNp05.0"}, {"awgn s/n": 10, "error rate": 0.0, "message length": 143, "mode": "PSK125RC10", "simulation string": "\"AWGN_SNp10.0\",1,10,0,0,0,0,0,0,0,0,0,0,0,0", "suffix": "AWGN_SNp10.0"}, {"awgn s/n": 15, "error rate": 0.0, "message length": 143, "mode": "PSK125RC10", "simulation string": "\"AWGN_SNp15.0\",1,15,0,0,0,0,0,0,0,0,0,0,0,0", "suffix": "AWGN_SNp15.0"}]